drfrf/__init__.py
drfrf/mixins.py
tests/__init__.py
tests/settings.py
tests/test_mixins.py
drfrf-0.0.2.dist-info/METADATA
drfrf-0.0.2.dist-info/WHEEL
drfrf-0.0.2.dist-info/top_level.txt
drfrf-0.0.2.dist-info/RECORD
